gcloud_cache/__init__.py
gcloud_cache/cache.py
gcloud_cache/storage.py
gcloud_cache-0.1.4.dist-info/METADATA
gcloud_cache-0.1.4.dist-info/WHEEL
gcloud_cache-0.1.4.dist-info/top_level.txt
gcloud_cache-0.1.4.dist-info/RECORD
