Metadata-Version: 2.1
Name: gcloud-cache
Version: 0.1.4
Summary: A Python package for caching data and files in Google Cloud Storage.
Home-page: https://github.com/lechplace/gcloud-cache
Author: Your Name
Author-email: lech.hubicki@gmail.com
License: UNKNOWN
Platform: UNKNOWN
Classifier: Programming Language :: Python :: 3
Classifier: License :: OSI Approved :: MIT License
Classifier: Operating System :: OS Independent
Requires-Python: >=3.6
Requires-Dist: google-cloud-storage
Requires-Dist: pyyaml
Requires-Dist: fpdf
